{
    "name": "アリシア",
    "id": 11201009,
    "skins": [
        {
            "name": "Base",
            "quotes": [
                {
                    "key": "メンバー募集",
                    "voice": "alicia_get_1.ogg",
                    "name": "メンバー募集",
                    "quote": "配達人アリシア、到着しました！　新人なのでご迷惑をかけるかもしれませんが、子供扱いは不要ですから。よろしくお願いします！"
                },
                {
                    "key": "ログインボイス",
                    "voice": "alicia_in_1.ogg",
                    "name": "ログインボイス",
                    "quote": "遅いですよ、リーダー。もう出発しちゃいますからね！"
                },
                {
                    "key": "待機ボイス1",
                    "voice": "alicia_main_1.ogg",
                    "name": "待機ボイス1",
                    "quote": "リーダーはここで仕事していてください。 その間、私は配達に行ってきます。 では…って、配達鞄を忘れるところでした…！"
                },
                {
                    "key": "待機ボイス2",
                    "voice": "alicia_main_2.ogg",
                    "name": "待機ボイス2",
                    "quote": "私もう子供じゃありませんから。配達人の仕事もプライドの仕事も、ちゃんとやりきりますよっ。頼みたいことがあったら、遠慮なく言ってください！"
                },
                {
                    "key": "待機ボイス3",
                    "voice": "alicia_main_3.ogg",
                    "name": "待機ボイス3",
                    "quote": "私は一人前の配達人ですから、どんな危険な場所でも行けますっ！　…ただそういうところに行くと母が心配するので、あんまり行ったことはありませんが…"
                },
                {
                    "key": "突破",
                    "voice": "alicia_stage_1.ogg",
                    "name": "突破",
                    "quote": "少しは大人っぽくなれましたかね！"
                },
                {
                    "key": "立ち絵獲得1",
                    "voice": "alicia_stage_2.ogg",
                    "name": "立ち絵獲得1",
                    "quote": "成長が早いですが、私はもっとできるはずです！　一緒に頑張りましょう、リーダー！"
                },
                {
                    "key": "立ち絵獲得2",
                    "voice": "alicia_stage_3.ogg",
                    "name": "立ち絵獲得2",
                    "quote": "今の私は、皆さんと同じ大人ですから！　どんな配達でもクエストでも、任せてください！"
                },
                {
                    "key": "覚醒",
                    "voice": "alicia_star_1.ogg",
                    "name": "覚醒",
                    "quote": "リーダーが協力してくれるから、私はもっと成長できるんです！"
                },
                {
                    "key": "好感度Lv1",
                    "voice": "alicia_interaction_1.ogg",
                    "name": "好感度Lv1",
                    "quote": "リーダー、何か配達物はありませんか？　今なら手が空いていますから、特急でお届けできますよ！"
                },
                {
                    "key": "好感度Lv3",
                    "voice": "alicia_interaction_2.ogg",
                    "name": "好感度Lv3",
                    "quote": "新人だとしても、他の皆さんと同じように接してくださいね。他の人たちがやっていることなら、私だってやりきってみせますから！"
                },
                {
                    "key": "好感度Lv5",
                    "voice": "alicia_interaction_3.ogg",
                    "name": "好感度Lv5",
                    "quote": "私は配達人ですからね。地図にある道もない道も、すべて覚えているんです。もし何かの役に立てそうなら声をかけてくださいね。"
                },
                {
                    "key": "好感度Lv7",
                    "voice": "alicia_interaction_4.ogg",
                    "name": "好感度Lv7",
                    "quote": "リーダーと一緒なら私、どこへでも行ける気がしますっ。さぁ、仕事を続けましょう！"
                },
                {
                    "key": "好感度Lv9",
                    "voice": "alicia_interaction_5.ogg",
                    "name": "好感度Lv9",
                    "quote": "手紙や物だけでなく、その気持ちを届けるのが私の仕事であって、責任なんです。…でも近頃は、ちょっと自信がないんです。私の気持ちは、ちゃんとリーダーに伝わってるのかなって…"
                },
                {
                    "key": "冒険者出陣",
                    "voice": "alicia_go_1.ogg",
                    "name": "冒険者出陣",
                    "quote": "どんな配達もクエストも、やり遂げましょう！"
                },
                {
                    "key": "攻撃1",
                    "voice": "alicia_battle_n_1.ogg",
                    "name": "攻撃1",
                    "quote": "どいて！"
                },
                {
                    "key": "攻撃2",
                    "voice": "alicia_battle_n_2.ogg",
                    "name": "攻撃2",
                    "quote": "はっ！"
                },
                {
                    "key": "攻撃3",
                    "voice": "alicia_battle_n_3.ogg",
                    "name": "攻撃3",
                    "quote": "許しません！"
                },
                {
                    "key": "攻撃4",
                    "voice": "alicia_battle_n_4.ogg",
                    "name": "攻撃4",
                    "quote": "えいっ！"
                },
                {
                    "key": "攻撃5",
                    "voice": "alicia_battle_n_5.ogg",
                    "name": "攻撃5",
                    "quote": "邪魔しないでください！"
                },
                {
                    "key": "被ダメージ1",
                    "voice": "alicia_battle_hit_1.ogg",
                    "name": "被ダメージ1",
                    "quote": "助けてっ…！"
                },
                {
                    "key": "被ダメージ2",
                    "voice": "alicia_battle_hit_2.ogg",
                    "name": "被ダメージ2",
                    "quote": "まだ大丈夫…！"
                },
                {
                    "key": "被ダメージ3",
                    "voice": "alicia_battle_hit_3.ogg",
                    "name": "被ダメージ3",
                    "quote": "うぅっ"
                },
                {
                    "key": "被ダメージ4",
                    "voice": "alicia_battle_hit_4.ogg",
                    "name": "被ダメージ4",
                    "quote": "わっ！"
                },
                {
                    "key": "被ダメージ5",
                    "voice": "alicia_battle_hit_5.ogg",
                    "name": "被ダメージ5",
                    "quote": "やっ"
                },
                {
                    "key": "被ダメージ6",
                    "voice": "alicia_battle_hit_6.ogg",
                    "name": "被ダメージ6",
                    "quote": "うっ、痛い…！"
                },
                {
                    "key": "戦闘不能",
                    "voice": "alicia_battle_die_1.ogg",
                    "name": "戦闘不能",
                    "quote": "やっぱりまだ、一人前じゃなかったみたいです…"
                },
                {
                    "key": "特技1",
                    "voice": "alicia_battle_h_1.ogg",
                    "name": "特技1",
                    "quote": "あなたは私を止められませんよ！"
                },
                {
                    "key": "特技2",
                    "voice": "alicia_battle_h_2.ogg",
                    "name": "特技2",
                    "quote": "子供だなんて思わないでください！"
                },
                {
                    "key": "奥義1",
                    "voice": "alicia_battle_c_1.ogg",
                    "name": "奥義1",
                    "quote": "私たちの行く道を邪魔するなんて、後悔しますよ！"
                },
                {
                    "key": "奥義2",
                    "voice": "alicia_battle_c_2.ogg",
                    "name": "奥義2",
                    "quote": "私はこのあたりの道をすべてわかってますからね、逃げられませんよ！"
                },
                {
                    "key": "戦闘勝利",
                    "voice": "alicia_win_1.ogg",
                    "name": "戦闘勝利",
                    "quote": "ふぅ。予定どおり、配達完了です！　さて、次の届け先は…"
                },
                {
                    "key": "戦闘失敗",
                    "voice": "alicia_fail_1.ogg",
                    "name": "戦闘失敗",
                    "quote": "これじゃ配達が間に合いませんっ…！"
                }
            ]
        }
    ]
}